ros_service_msgs-2.3.0.data/data/include/service_msgs/service_msgs/msg/rosidl_generator_c__visibility_control.h
ros_service_msgs-2.3.0.data/data/include/service_msgs/service_msgs/msg/rosidl_generator_cpp__visibility_control.hpp
ros_service_msgs-2.3.0.data/data/include/service_msgs/service_msgs/msg/rosidl_typesupport_fastrtps_c__visibility_control.h
ros_service_msgs-2.3.0.data/data/include/service_msgs/service_msgs/msg/rosidl_typesupport_fastrtps_cpp__visibility_control.h
ros_service_msgs-2.3.0.data/data/include/service_msgs/service_msgs/msg/rosidl_typesupport_introspection_c__visibility_control.h
ros_service_msgs-2.3.0.data/data/include/service_msgs/service_msgs/msg/service_event_info.h
ros_service_msgs-2.3.0.data/data/include/service_msgs/service_msgs/msg/service_event_info.hpp
ros_service_msgs-2.3.0.data/data/include/service_msgs/service_msgs/msg/detail/service_event_info__builder.hpp
ros_service_msgs-2.3.0.data/data/include/service_msgs/service_msgs/msg/detail/service_event_info__description.c
ros_service_msgs-2.3.0.data/data/include/service_msgs/service_msgs/msg/detail/service_event_info__functions.c
ros_service_msgs-2.3.0.data/data/include/service_msgs/service_msgs/msg/detail/service_event_info__functions.h
ros_service_msgs-2.3.0.data/data/include/service_msgs/service_msgs/msg/detail/service_event_info__rosidl_typesupport_fastrtps_c.h
ros_service_msgs-2.3.0.data/data/include/service_msgs/service_msgs/msg/detail/service_event_info__rosidl_typesupport_fastrtps_cpp.hpp
ros_service_msgs-2.3.0.data/data/include/service_msgs/service_msgs/msg/detail/service_event_info__rosidl_typesupport_introspection_c.h
ros_service_msgs-2.3.0.data/data/include/service_msgs/service_msgs/msg/detail/service_event_info__rosidl_typesupport_introspection_cpp.hpp
ros_service_msgs-2.3.0.data/data/include/service_msgs/service_msgs/msg/detail/service_event_info__struct.h
ros_service_msgs-2.3.0.data/data/lib/python3.14/site-packages/service_msgs-2.3.0-py3.14.egg-info/PKG-INFO
ros_service_msgs-2.3.0.data/data/lib/python3.14/site-packages/service_msgs-2.3.0-py3.14.egg-info/SOURCES.txt
ros_service_msgs-2.3.0.data/data/lib/python3.14/site-packages/service_msgs-2.3.0-py3.14.egg-info/dependency_links.txt
ros_service_msgs-2.3.0.data/data/lib/python3.14/site-packages/service_msgs-2.3.0-py3.14.egg-info/top_level.txt
ros_service_msgs-2.3.0.dist-info/METADATA
ros_service_msgs-2.3.0.dist-info/WHEEL
ros_service_msgs-2.3.0.dist-info/top_level.txt
ros_service_msgs-2.3.0.dist-info/RECORD
