Metadata-Version: 2.4
Name: ros-service-msgs
Version: 2.3.0
Summary: A ROS package providing common message types used by ROS services, including ServiceEventInfo for introspection.
Requires-Dist: ros-rosidl-core-runtime~=0.3.1
Requires-Dist: ros-builtin-interfaces~=2.3.0
Dynamic: description
Dynamic: description-content-type
Dynamic: requires-dist
Dynamic: summary
